wid/__init__.py
wid/cli/__init__.py
wid/cli/web_img_crawler.py
wid/cli/web_img_downloader.py
wid/file/__init__.py
wid/file/utils.py
wid/web/__init__.py
wid/web/url.py
wid/web/bot/__init__.py
wid/web/bot/instructions.py
wid/web/bot/webcrawler.py
wid/web/img/__init__.py
wid/web/img/save.py
wid/web/img/scrape.py
webpage_image_downloader-0.1.2.dist-info/LICENCE
webpage_image_downloader-0.1.2.dist-info/METADATA
webpage_image_downloader-0.1.2.dist-info/WHEEL
webpage_image_downloader-0.1.2.dist-info/entry_points.txt
webpage_image_downloader-0.1.2.dist-info/top_level.txt
webpage_image_downloader-0.1.2.dist-info/RECORD
