Metadata-Version: 2.1
Name: webpage-image-downloader
Version: 0.1.2
Summary: Tool for extracting and saving specific images from websites.
Home-page: https://github.com/A-Bak/webpage-img-downloader
Author: A-Bak
Author-email: adam.bak753@gmail.com
License: UNKNOWN
Keywords: webscraping webcrawler image img downloader selenium-python
Platform: UNKNOWN
Classifier: Programming Language :: Python :: 3
Classifier: License :: OSI Approved :: MIT License
Classifier: Operating System :: OS Independent
Requires-Python: >=3.6
License-File: LICENCE
Requires-Dist: async-generator (==1.10)
Requires-Dist: attrs (==21.4.0)
Requires-Dist: certifi (==2021.10.8)
Requires-Dist: cffi (==1.15.0)
Requires-Dist: charset-normalizer (==2.0.12)
Requires-Dist: click (==8.0.4)
Requires-Dist: colorama (==0.4.4)
Requires-Dist: cryptography (==36.0.2)
Requires-Dist: h11 (==0.13.0)
Requires-Dist: idna (==3.3)
Requires-Dist: outcome (==1.1.0)
Requires-Dist: pycparser (==2.21)
Requires-Dist: pyOpenSSL (==22.0.0)
Requires-Dist: pyperclip (==1.8.2)
Requires-Dist: PySocks (==1.7.1)
Requires-Dist: requests (==2.27.1)
Requires-Dist: selenium (==4.1.3)
Requires-Dist: sniffio (==1.2.0)
Requires-Dist: sortedcontainers (==2.4.0)
Requires-Dist: soupsieve (==2.3.1)
Requires-Dist: trio (==0.20.0)
Requires-Dist: trio-websocket (==0.9.2)
Requires-Dist: urllib3 (==1.26.9)
Requires-Dist: webdriver-manager (==3.5.4)
Requires-Dist: wsproto (==1.1.0)
